{
	"services": [
		{
			"active": true,
			"id":"webos",
			"name":"webOS",
			"type": ["build", "test"],
			"command":"@NODE@", "params":[
				"@PLUGINDIR@/ares/server/bdWebos.js", "-l", "http", "-I", "@INSTALLDIR@", "-P", "/webos", "-p", "0", "-t", "240000"
			],
			"pluginClient": "@PLUGINURL@/ares/client/package.js",
			"useJsonp":false,
			"verbose": false,
			"respawn": false
		},
		{
			"id": "genZip",
			"sources": [
				{
				"id": "WebOS-Ports",
				"type": null
				}, 
				{
					"id": "bootplate-sample-local",
					"Xtype": "template",
					"type": null,
					"description": "Local Bootplate Sample(Local)",
					"deps": ["webos-app-config"],
					"files": [
						{
							"url": "@PLUGINDIR@/../bootplate-folder-name",
							"excluded": [	
								".git/",
								"enyo/.git/",
								"lib/enyo-sample/.git/"
							]
						}
					]
				},
				{
					"id": "bootplate-web",
					"type": "template",
					"version": "0.0.1",
					"isDefault": false,
					"description": "Basic web template for webOS - none enyo library.",
					"class":"basic",
					"deps": ["webappinfo", "webicon"],
					"files": [
						{
							"url": "@PLUGINDIR@/templates/bootplate-web.zip"
						}
					]
				},
				{
					"id": "bootplate-moonstone",
					"type": "template",
					"version": "2.3.0",
					"isDefault": true,
					"description": "Enyo moonstone bootplate",
					"class":"moonstone",
					"deps": ["enyoappinfo", "enyoicon"],
					"files": [
						{
							"url": "@PLUGINDIR@/templates/bootplate-moonstone",
							"excluded": [	
								".git",
								".gitignore",
								".gitmodules",
								"enyo/.git",
								"enyo/.gitignore",
								"lib/enyo-cordova/.git",
								"lib/enyo-ilib/.git",
								"lib/enyo-webos/.git",
								"lib/layout/.git",
								"lib/moonstone/.git",
								"lib/moonstone/.gitignore",
								"lib/spotlight/.git"
							]
						}
					]
				},
				{
					"id": "bootplate-2.3.0-pre.12",
					"Xtype": "template",
					"type": null,
					"version": "2.3.0-pre.12",
					"isDefault": false,
					"description": "Enyo bootplate 2.3.0 (No webOS specific library)",
					"class":"basic",
					"deps": ["webappinfo"],
					"files": [
						{
							"url": "http://enyojs.com/archive/bootplate-2.3.0-pre.12.zip",
							"prefixToRemove": "bootplate",
							"excluded": [
								"bootplate/api/"
							]
						}
					]
				},
				{
					"id": "bootplate-2.2.0",
					"type": "null",
					"version": "2.2.0",
					"description": "Enyo bootplate 2.2.0",
					"deps": ["webos-app-config"],
					"class":"basic",
					"files": [
						{
							"url": "http://enyojs.com/archive/bootplate-2.2.0.zip",
							"prefixToRemove": "bootplate",
							"excluded": [
								"bootplate/api/"
							]
						}
					]
				},
				{
					"id": "bootplate-2.1.1",
					"type": "null",
					"version": "2.1.1",
					"description": "Enyo bootplate 2.1.1",
					"deps": ["webos-app-config"],
					"class":"basic",
					"files": [
						{
							"url": "http://enyojs.com/archive/bootplate-2.1.1.zip",
							"prefixToRemove": "bootplate",
							"excluded": [
								"bootplate/api/"
							]
						}
					]
				},
				{
					"id": "webos-service-helloworld",
					"Xtype": "webosService",
					"type" : null,
					"version": "0.0.1",
					"description": "webOS Node.js Service Template",
					"files": [
						{
							"url": "http://enyojs.com/webos/webos-service-config.zip",
							"prefixToAdd": "services/com.example.helloworld"
						}
					]
				},
				{
					"id": "webos-service",
					"type": "webosService",
					"version": "0.0.1",
					"description": "webOS Node.js Service Template",
					"files": [
						{
							"url": "@PLUGINDIR@/templates/webos-service",
							"prefixToAdd": ""
						}
					],
					"filesubstitution": [
						"package.json",
						"services.json",
						"helloworld_webos_service.js",
						"helloclient.js"
					]
				},
				{
					"id": "webos-app-config",
					"Xtype": "webosConfig",
					"type": null,
					"version": "0.0.1",
					"description": "webOS Applicatin Config data",
					"files": [
						{
							"url": "http://enyojs.com/webos/webos-app-config.zip"
						}
					]
				},
				{
					"id": "webappinfo",
					"type": "appinfo",
					"version": "0.0.1",
					"description": "minimal appinfo.json for webOS Applicatin",
					"files": [
						{
							"url": "@PLUGINDIR@/templates/webappinfo"
						}
					],
					"filesubstitution": [
						"appinfo.json"
					]
				},
				{
					"id": "enyoappinfo",
					"type": "appinfo",
					"version": "0.0.1",
					"description": "appinfo.json to use built-in enyo framework on WebOS Device",
					"files": [
						{
							"url": "@PLUGINDIR@/templates/enyoappinfo"
						}
					],
					"filesubstitution": [
						"appinfo.json"
					]
				},
				{
					"id": "webicon",
					"type": "image",
					"version": "0.0.1",
					"description": "normal icon files [icon.png (80x80), largeIcon.png (130x130)]",
					"files": [
						{
							"url": "@PLUGINDIR@/templates/webicon"
						}
					]
				},
				{
					"id": "enyoicon",
					"type": "image",
					"version": "0.0.1",
					"description": "enyo icon files [icon.png (80x80), largeIcon.png (130x130)]",
					"files": [
						{
							"url": "@PLUGINDIR@/templates/enyoicon"
						}
					]
				},
				{
					"id": "bootplate-2.3.0",
					"Xtype": "template",
					"type": null,
					"version": "2.3.0",
					"description": "Enyo bootplate 2.3.0 (No webOS specific library)",
					"class":"basic",
					"deps": ["enyoappinfo", "enyoicon"],
					"files": [
						{
							"url": "@PLUGINDIR@/templates/bootplate-moonstone",
							"excluded": [	
								".git",
								".gitignore",
								".gitmodules",
								"enyo/.git",
								"enyo/.gitignore",
								"lib/enyo-cordova",
								"lib/enyo-ilib",
								"lib/enyo-webos",
								"lib/layout/.git",
								"lib/moonstone/.git",
								"lib/moonstone/.gitignore",
								"lib/spotlight/.git"
							]
						}
					]
				},
				{
					"id": "enyo",
					"type": "library",
					"version": "2.3.0",
					"description": "Enyo library",
					"files": [
						{
							"url": "@PLUGINDIR@/templates/bootplate-moonstone/enyo",
							"prefixToAdd": "enyo",
							"excluded": [	
								".git",
								".gitignore",
								".gitmodules",
								"enyo/.git",
								"enyo/.gitignore"
							]
						}
					]
				},
				{
					"id": "enyo-cordova",
					"type": "library",
					"version": "2.3.0",
					"description": "Enyo cordova library",
					"files": [
						{
							"url": "@PLUGINDIR@/templates/bootplate-moonstone/lib/enyo-cordova",
							"prefixToAdd": "lib/enyo-cordova",
							"excluded": [	
								".git",
								".gitignore",
								".gitmodules",
								"lib/enyo-cordova/.git"
							]
						}
					]
				},
				{
					"id": "enyo-ilib",
					"type": "library",
					"version": "2.3.0",
					"description": "Enyo ilib globalization/internationalization library",
					"files": [
						{
							"url": "@PLUGINDIR@/templates/bootplate-moonstone/lib/enyo-ilib",
							"prefixToAdd": "lib/enyo-ilib",
							"excluded": [	
								".git",
								".gitignore",
								".gitmodules",
								"lib/enyo-ilib/.git"
							]
						}
					]
				},
				{
					"id": "enyo-webos",
					"type": "library",
					"version": "2.3.0",
					"description": "Enyo library for webOS",
					"files": [
						{
							"url": "@PLUGINDIR@/templates/bootplate-moonstone/lib/enyo-webos",
							"prefixToAdd": "lib/enyo-webos",
							"excluded": [	
								".git",
								".gitignore",
								".gitmodules",
								"lib/enyo-webos/.git"
							]
						}
					]
				},
				{
					"id": "enyo-layout",
					"type": "library",
					"version": "2.3.0",
					"description": "Enyo layout library",
					"files": [
						{
							"url": "@PLUGINDIR@/templates/bootplate-moonstone/lib/layout",
							"prefixToAdd": "lib/layout",
							"excluded": [	
								".git",
								".gitignore",
								".gitmodules",
								"lib/layout/.git"
							]
						}
					]
				},
				{
					"id": "enyo-moonstone",
					"type": "library",
					"version": "2.3.0",
					"description": "Enyo moonstone library",
					"files": [
						{
							"url": "@PLUGINDIR@/templates/bootplate-moonstone/lib/moonstone",
							"prefixToAdd": "lib/moonstone",
							"excluded": [	
								".git",
								".gitignore",
								".gitmodules",
								"lib/moonstone/.git"
							]
						}
					]
				},
				{
					"id": "enyo-spotlight",
					"type": "library",
					"version": "2.3.0",
					"description": "Enyo spotlight library",
					"files": [
						{
							"url": "@PLUGINDIR@/templates/bootplate-moonstone/lib/spotlight",
							"prefixToAdd": "lib/spotlight",
							"excluded": [	
								".git",
								".gitignore",
								".gitmodules",
								"lib/spotlight/.git"
							]
						}
					]
				}
			]
		}
	]
}
